{"dataset": "predator-1f43a", "cubes": [{"cube_index": 0, "cube_player": "predator", "cube_uuid": "924006e6-2188-405e-9d5a-703417defb4a", "cube_emoticon": "1f43a", "cube_firstname": "Wolf", "cube_active": true, "cube_display": true, "cube_scale_factor": 0.90115, "cube_type": 3, "cube_color_class": "r", "cube_color": [0.67451, 0.29412, 0.29804, 1.0], "cube_material": 0, "cube_surface": "surface-4-berber-512x512", "cube_texture_index": 2, "cube_texture_map": [0.0, 0.0, 0.16666, 0.0, 0.16666, 1.0, 0.0, 1.0, 0.33333, 0.0, 0.5, 0.0, 0.5, 1.0, 0.33333, 1.0, 0.83333, 0.0, 0.83333, 1.0, 0.66666, 1.0, 0.66666, 0.0, 1.0, 0.0, 1.0, 1.0, 0.83333, 1.0, 0.83333, 0.0, 0.16666, 1.0, 0.16666, 0.0, 0.33333, 0.0, 0.33333, 1.0, 0.66666, 0.0, 0.66666, 1.0, 0.5, 1.0, 0.5, 0.0], "cube_parameters": {}, "spatial_position": [0.0, 0.90215, 0.0], "spatial_rotation": [0.0, 0.0, 0.0], "spatial_gaze": [0.0, 0.0], "spatial_radius": 1.27442, "spatial_destination": [0.0, 0.0, 0.0], "spatial_velocity": 0.0, "resource_energy": 100.0}], "textures": [{"texture_index": 2, "texture_filename": "training/textures/1f43a-texture.png"}]}